ServoRPi/__init__.py
ServoRPi/servo.py
ServoRPi-0.1.6.dist-info/METADATA
ServoRPi-0.1.6.dist-info/WHEEL
ServoRPi-0.1.6.dist-info/top_level.txt
ServoRPi-0.1.6.dist-info/RECORD
