Metadata-Version: 2.1
Name: ServoRPi
Version: 0.1.6
Summary: For Control Servo Easily By A Raspberry Pi
Home-page: https://github.com/Aiversity/My-Libraries/tree/main/ServoRPi
Author: AI Versity
Author-email: hello.aiversity@gmail.com
License: Apache License 2.0
Platform: UNKNOWN
Requires-Dist: rpi.gpio
